baduk/__init__.py
baduk/__main__.py
baduk/action/__init__.py
baduk/action/load_sgf.py
baduk/action/start_game.py
baduk/command/__init__.py
baduk/command/add_to_adjacent_group_of_stones.py
baduk/command/chain_of_command.py
baduk/command/command_types.py
baduk/command/create_group_of_stones.py
baduk/command/merge_with_adjacent_group_of_stones.py
baduk/command/remove_dead_stones.py
baduk/constants/__init__.py
baduk/constants/constants.py
baduk/constants/resource_path.py
baduk/dialog/__init__.py
baduk/dialog/board_set_up_dialog.py
baduk/dialog/menu_action_dialog.py
baduk/dialog/player_action_dialog.py
baduk/enums/__init__.py
baduk/enums/enums.py
baduk/exception/__init__.py
baduk/exception/exceptions.py
baduk/game/__init__.py
baduk/game/board.py
baduk/game/board_stack.py
baduk/game/game.py
baduk/game/move_log.py
baduk/game/player.py
baduk/game/point.py
baduk/game/turn.py
baduk/main.py
baduk/service/__init__.py
baduk/service/move_from_sgf.py
baduk/stones/__init__.py
baduk/stones/group_of_stones.py
baduk/stones/group_of_stones_collection.py
baduk/stones/stone_link.py
baduk/templates/blank.txt
baduk/templates/error.txt
baduk/templates/menu.txt
baduk/ui/__init__.py
baduk/ui/action/__init__.py
baduk/ui/action/action.py
baduk/ui/action/action_collection.py
baduk/ui/action/action_item.py
baduk/ui/pagination.py
baduk/ui/style.py
baduk/ui/user_input.py
baduk/ui/user_menu.py
baduk/ui/view.py
baduk/validation/__init__.py
baduk/validation/move_validation.py
baduk-1.0.4.dist-info/entry_points.txt
baduk-1.0.4.dist-info/WHEEL
baduk-1.0.4.dist-info/METADATA
baduk-1.0.4.dist-info/RECORD
